bcapi/.vscode/setting.json
bcapi/__init__.py
bcapi/cache.py
bcapi/card_table_cards.py
bcapi/card_table_columns.py
bcapi/card_table_steps.py
bcapi/card_tables.py
bcapi/client.py
bcapi/message_boards.py
bcapi/message_types.py
bcapi/messages.py
bcapi/operations.py
bcapi/people.py
bcapi/projects.py
bcapi/recordings.py
bcapi/schedule_entries.py
bcapi/schedules.py
bcapi/scripts/auth.py
bcapi/scripts/utils.py
bcapi/todolist_groups.py
bcapi/todolists.py
bcapi/todos.py
bcapi/todosets.py
bcapi-1.1.0.dist-info/METADATA
bcapi-1.1.0.dist-info/WHEEL
bcapi-1.1.0.dist-info/entry_points.txt
bcapi-1.1.0.dist-info/licenses/LICENSE
bcapi-1.1.0.dist-info/RECORD
