Metadata-Version: 2.4
Name: bcapi
Version: 1.1.0
Summary: Python client wrapper for Basecamp API
License: MIT
License-File: LICENSE
Keywords: basecamp,api,client
Author: Julian Mann
Author-email: julian.mann@gmail.com
Requires-Python: >=3.11,<4.0
Classifier: Intended Audience :: Developers
Classifier: License :: OSI Approved :: MIT License
Classifier: Programming Language :: Python :: 3
Classifier: Programming Language :: Python :: 3.11
Classifier: Programming Language :: Python :: 3.12
Classifier: Programming Language :: Python :: 3.13
Classifier: Programming Language :: Python :: 3.14
Requires-Dist: jinja2 (>=3.1.4,<4.0.0)
Requires-Dist: jmespath (>=1.0.1,<2.0.0)
Requires-Dist: requests (>=2.32.0,<3.0.0)
Project-URL: Documentation, https://github.com/hoolymama/bcapi
Project-URL: Homepage, https://github.com/hoolymama/bcapi
Project-URL: Repository, https://github.com/hoolymama/bcapi
